status_cake_exporter/__init__.py
status_cake_exporter/_logging.py
status_cake_exporter/_status_cake.py
status_cake_exporter/_test_collector.py
status_cake_exporter/app.py
status_cake_exporter-1.1.0.dist-info/entry_points.txt
status_cake_exporter-1.1.0.dist-info/LICENSE
status_cake_exporter-1.1.0.dist-info/METADATA
status_cake_exporter-1.1.0.dist-info/WHEEL
status_cake_exporter-1.1.0.dist-info/RECORD
