Metadata-Version: 2.1
Name: status-cake-exporter
Version: 1.1.0
Summary: 
License: MIT
Author: Craig Gumbley
Author-email: craiggumbley@gmail.com
Requires-Python: >=3.10,<4.0
Classifier: License :: OSI Approved :: MIT License
Classifier: Programming Language :: Python :: 3
Classifier: Programming Language :: Python :: 3.10
Classifier: Programming Language :: Python :: 3.11
Classifier: Programming Language :: Python :: 3.12
Requires-Dist: prometheus-client (==0.20.0)
Requires-Dist: requests (>=2.31.0,<3.0.0)
Requires-Dist: statuscake-py (>=1.1.0b1,<2.0.0)
Requires-Dist: typer (>=0.9.0,<0.10.0)
Requires-Dist: types-requests (>=2.31.0,<3.0.0)
Requires-Dist: typing-extensions (>=4.9.0,<5.0.0)
